{
	"files": [
		{
			"path": "array-methods.js",
			"bookmarks": [
				{
					"line": 0,
					"column": 0,
					"label": ""
				},
				{
					"line": 13,
					"column": 0,
					"label": ""
				},
				{
					"line": 40,
					"column": 0,
					"label": ""
				},
				{
					"line": 47,
					"column": 0,
					"label": ""
				},
				{
					"line": 80,
					"column": 0,
					"label": ""
				},
				{
					"line": 95,
					"column": 0,
					"label": ""
				},
				{
					"line": 111,
					"column": 0,
					"label": ""
				},
				{
					"line": 141,
					"column": 0,
					"label": ""
				},
				{
					"line": 162,
					"column": 0,
					"label": ""
				},
				{
					"line": 176,
					"column": 0,
					"label": ""
				},
				{
					"line": 190,
					"column": 0,
					"label": ""
				},
				{
					"line": 208,
					"column": 0,
					"label": ""
				},
				{
					"line": 230,
					"column": 0,
					"label": ""
				},
				{
					"line": 250,
					"column": 0,
					"label": ""
				},
				{
					"line": 272,
					"column": 0,
					"label": ""
				},
				{
					"line": 285,
					"column": 0,
					"label": ""
				},
				{
					"line": 304,
					"column": 0,
					"label": ""
				},
				{
					"line": 317,
					"column": 0,
					"label": ""
				},
				{
					"line": 328,
					"column": 0,
					"label": ""
				},
				{
					"line": 342,
					"column": 0,
					"label": ""
				},
				{
					"line": 380,
					"column": 0,
					"label": ""
				},
				{
					"line": 392,
					"column": 0,
					"label": ""
				},
				{
					"line": 417,
					"column": 0,
					"label": ""
				},
				{
					"line": 428,
					"column": 0,
					"label": ""
				},
				{
					"line": 441,
					"column": 0,
					"label": ""
				},
				{
					"line": 457,
					"column": 0,
					"label": ""
				},
				{
					"line": 519,
					"column": 0,
					"label": ""
				},
				{
					"line": 523,
					"column": 0,
					"label": ""
				},
				{
					"line": 542,
					"column": 0,
					"label": ""
				},
				{
					"line": 551,
					"column": 0,
					"label": ""
				},
				{
					"line": 570,
					"column": 0,
					"label": ""
				},
				{
					"line": 601,
					"column": 8,
					"label": ""
				},
				{
					"line": 654,
					"column": 0,
					"label": ""
				},
				{
					"line": 677,
					"column": 28,
					"label": ""
				}
			]
		},
		{
			"path": "string-methods.js",
			"bookmarks": [
				{
					"line": 14,
					"column": 0,
					"label": ""
				},
				{
					"line": 28,
					"column": 0,
					"label": ""
				},
				{
					"line": 46,
					"column": 0,
					"label": ""
				},
				{
					"line": 64,
					"column": 0,
					"label": ""
				},
				{
					"line": 89,
					"column": 0,
					"label": ""
				},
				{
					"line": 96,
					"column": 1,
					"label": ""
				},
				{
					"line": 112,
					"column": 0,
					"label": ""
				},
				{
					"line": 138,
					"column": 0,
					"label": ""
				},
				{
					"line": 154,
					"column": 0,
					"label": ""
				},
				{
					"line": 179,
					"column": 11,
					"label": ""
				},
				{
					"line": 196,
					"column": 1,
					"label": ""
				},
				{
					"line": 204,
					"column": 0,
					"label": ""
				},
				{
					"line": 218,
					"column": 0,
					"label": ""
				},
				{
					"line": 236,
					"column": 42,
					"label": ""
				},
				{
					"line": 261,
					"column": 18,
					"label": ""
				},
				{
					"line": 269,
					"column": 56,
					"label": ""
				},
				{
					"line": 272,
					"column": 2,
					"label": ""
				},
				{
					"line": 283,
					"column": 10,
					"label": ""
				},
				{
					"line": 310,
					"column": 0,
					"label": ""
				},
				{
					"line": 324,
					"column": 22,
					"label": ""
				},
				{
					"line": 342,
					"column": 44,
					"label": ""
				},
				{
					"line": 369,
					"column": 0,
					"label": ""
				},
				{
					"line": 399,
					"column": 30,
					"label": ""
				},
				{
					"line": 410,
					"column": 0,
					"label": ""
				},
				{
					"line": 425,
					"column": 29,
					"label": ""
				},
				{
					"line": 452,
					"column": 0,
					"label": ""
				},
				{
					"line": 467,
					"column": 37,
					"label": ""
				},
				{
					"line": 478,
					"column": 0,
					"label": ""
				},
				{
					"line": 490,
					"column": 166,
					"label": ""
				},
				{
					"line": 494,
					"column": 0,
					"label": ""
				},
				{
					"line": 514,
					"column": 4,
					"label": ""
				},
				{
					"line": 522,
					"column": 0,
					"label": ""
				}
			]
		},
		{
			"path": "dom-manipulation.js",
			"bookmarks": [
				{
					"line": 2,
					"column": 32,
					"label": ""
				},
				{
					"line": 8,
					"column": 0,
					"label": ""
				},
				{
					"line": 12,
					"column": 18,
					"label": ""
				},
				{
					"line": 19,
					"column": 0,
					"label": ""
				},
				{
					"line": 32,
					"column": 17,
					"label": ""
				},
				{
					"line": 37,
					"column": 19,
					"label": ""
				},
				{
					"line": 57,
					"column": 20,
					"label": ""
				},
				{
					"line": 62,
					"column": 0,
					"label": ""
				},
				{
					"line": 68,
					"column": 21,
					"label": ""
				}
			]
		},
		{
			"path": "math-methods.js",
			"bookmarks": [
				{
					"line": 3,
					"column": 16,
					"label": ""
				},
				{
					"line": 8,
					"column": 17,
					"label": ""
				},
				{
					"line": 13,
					"column": 22,
					"label": ""
				},
				{
					"line": 18,
					"column": 23,
					"label": ""
				},
				{
					"line": 22,
					"column": 25,
					"label": ""
				},
				{
					"line": 27,
					"column": 23,
					"label": ""
				},
				{
					"line": 31,
					"column": 31,
					"label": ""
				},
				{
					"line": 36,
					"column": 31,
					"label": ""
				},
				{
					"line": 40,
					"column": 33,
					"label": ""
				},
				{
					"line": 44,
					"column": 0,
					"label": ""
				},
				{
					"line": 54,
					"column": 26,
					"label": ""
				},
				{
					"line": 58,
					"column": 22,
					"label": ""
				},
				{
					"line": 63,
					"column": 0,
					"label": ""
				},
				{
					"line": 66,
					"column": 27,
					"label": ""
				}
			]
		}
	]
}